{
  "code": 200,
  "data": {
    "componentCode": "C1523",
    "componentBrandEn": "FH (Guangdong Fenghua Advanced Tech)",
    "componentModelEn": "0402B102K500NT",
    "componentImageUrl": "",
    "productBigImageAccessId": "8552475976585138176",
    "dataManualUrl": "https://www.lcsc.com/datasheet/lcsc_datasheet_2304140030_FH--Guangdong-Fenghua-Advanced-Tech-0402B102K500NT_C1523.pdf",
    "dataManualFileAccessId": "8579707266641018880",
    "dataManualOfficialLink": "",
    "componentName": "FH 0402B102K500NT",
    "minImage": "",
    "minImageAccessId": "8552475977160028160",
    "imageList": [
      {
        "productImage": null,
        "productImageAccessId": "8552475977160028160",
        "productBigImage": null,
        "productBigImageAccessId": "8552475976585138176",
        "fileType": 1
      },
      {
        "productImage": null,
        "productImageAccessId": "8553212889332015104",
        "productBigImage": null,
        "productBigImageAccessId": "8553212888564322305",
        "fileType": 2
      },
      {
        "productImage": null,
        "productImageAccessId": "8552475997112332288",
        "productBigImage": null,
        "productBigImageAccessId": "8552475996520935424",
        "fileType": 4
      },
      {
        "productImage": null,
        "productImageAccessId": "8578671801498861569",
        "productBigImage": null,
        "productBigImageAccessId": "8578671800560959488",
        "fileType": 3
      }
    ],
    "manufacturerBlackFlag": null,
    "componentNameEn": "FH 0402B102K500NT",
    "componentSpecificationEn": "0402",
    "describe": "1nF 50V X7R ±10% 0402 Multilayer Ceramic Capacitors MLCC - SMD/SMT ROHS",
    "attributes": [
      {
        "attribute_name_en": "Voltage Rating",
        "component_code": "C1523",
        "attribute_value_name": "50V"
      },
      {
        "attribute_name_en": "Tolerance",
        "component_code": "C1523",
        "attribute_value_name": "±10%"
      },
      {
        "attribute_name_en": "Capacitance",
        "component_code": "C1523",
        "attribute_value_name": "1nF"
      },
      {
        "attribute_name_en": "Temperature Coefficient",
        "component_code": "C1523",
        "attribute_value_name": "X7R"
      }
    ],
    "rankScore": null,
    "firstSortName": "Capacitors",
    "secondSortName": "Multilayer Ceramic Capacitors MLCC - SMD/SMT",
    "componentBrandHigh": null,
    "remarkHigh": null,
    "componentModelHigh": null,
    "componentCodeHigh": null,
    "componentSpecificationHigh": null,
    "rohsFlag": 1,
    "assemblyComponentFlag": false,
    "lcscComponentId": 1875,
    "componentDesignator": "C",
    "componentSource": "shop",
    "stockCount": 999658,
    "overseasStockCount": 999658,
    "prices": [
      {
        "componentPriceKeyId": null,
        "componentPriceAccessId": null,
        "lcscComponentId": null,
        "componentCode": "C1523",
        "startNumber": 1,
        "endNumber": 999,
        "productPrice": 0.0011,
        "erpComponentPriceKeyId": 243028990,
        "createTime": null,
        "updateTime": null,
        "deleted": false,
        "lcscPriceRangeCoefficient": 1
      },
      {
        "componentPriceKeyId": null,
        "componentPriceAccessId": null,
        "lcscComponentId": null,
        "componentCode": "C1523",
        "startNumber": 1000,
        "endNumber": 2999,
        "productPrice": 0.0008,
        "erpComponentPriceKeyId": 243029029,
        "createTime": null,
        "updateTime": null,
        "deleted": false,
        "lcscPriceRangeCoefficient": 1
      },
      {
        "componentPriceKeyId": null,
        "componentPriceAccessId": null,
        "lcscComponentId": null,
        "componentCode": "C1523",
        "startNumber": 3000,
        "endNumber": 9999,
        "productPrice": 0.0007,
        "erpComponentPriceKeyId": 243029019,
        "createTime": null,
        "updateTime": null,
        "deleted": false,
        "lcscPriceRangeCoefficient": 1
      },
      {
        "componentPriceKeyId": null,
        "componentPriceAccessId": null,
        "lcscComponentId": null,
        "componentCode": "C1523",
        "startNumber": 10000,
        "endNumber": 49999,
        "productPrice": 0.0006,
        "erpComponentPriceKeyId": 243028999,
        "createTime": null,
        "updateTime": null,
        "deleted": false,
        "lcscPriceRangeCoefficient": 1
      },
      {
        "componentPriceKeyId": null,
        "componentPriceAccessId": null,
        "lcscComponentId": null,
        "componentCode": "C1523",
        "startNumber": 50000,
        "endNumber": 50199,
        "productPrice": 0.0005,
        "erpComponentPriceKeyId": 243029010,
        "createTime": null,
        "updateTime": null,
        "deleted": false,
        "lcscPriceRangeCoefficient": 1
      },
      {
        "componentPriceKeyId": null,
        "componentPriceAccessId": null,
        "lcscComponentId": null,
        "componentCode": "C1523",
        "startNumber": 50200,
        "endNumber": -1,
        "productPrice": 0.0005,
        "erpComponentPriceKeyId": 243029028,
        "createTime": null,
        "updateTime": null,
        "deleted": false,
        "lcscPriceRangeCoefficient": 1
      }
    ],
    "jlcPrices": null,
    "encapsulationUnit": "PCS",
    "encapsulationNumber": 10000,
    "componentTypeEn": null,
    "xrayFlag": false,
    "componentLibraryType": "base",
    "leastNumber": 20,
    "leastNumberPrice": 0.004,
    "lcscGoodsUrl": "https://www.lcsc.com/product-detail/multilayer-ceramic-capacitors-mlcc-smd-smt_fh-guangdong-fenghua-advanced-tech-0402b102k500nt_C1523.html/?href=jlc-SMT/?href=jlc-SMT",
    "erpComponentName": "1nF ±10% 50V",
    "lossNumber": 10,
    "secondTypeNameEn": "Multilayer Ceramic Capacitors MLCC - SMD/SMT",
    "firstTypeNameEn": "Capacitors",
    "secondTypeNameId": 2929,
    "firstTypeNameId": 2,
    "warehouseCode": "sz",
    "warehouseName": "深圳",
    "canPresaleNumber": 771723,
    "minPresaleNumber": 0,
    "theRatio": null,
    "componentStatus": "yes",
    "assemblyMode": "smtWeld",
    "assemblyModeBatch": "smtWeld",
    "assemblyProcess": "SMT",
    "minPurchaseNum": 1,
    "initialPrice": 0.0011,
    "minPresalePrice": null,
    "componentPresaleType": null,
    "preMinPurchaseNum": 10000,
    "providerInfos": null,
    "componentProductType": 0,
    "isBuyComponent": "1",
    "noBuyReason": null,
    "replaceUrlSuffix": null,
    "componentAlternativesCode": null,
    "alternativesLcscComponentId": null,
    "leastPatchNumber": 20,
    "fixtureFlag": false,
    "fullReelPrice": null,
    "recentBuyNum": null,
    "recentBuyUnitPrice": null,
    "buyCustomerCode": null,
    "eccnCode": "",
    "allowPostFlag": true,
    "overseasComponentCatalogBizKey": 385244381135388676,
    "overseasComponentBrandBizKey": "385285307644252161",
    "catalogBlackFlag": null,
    "shopShowPriceFlag": true,
    "shopShowForeignPriceFlag": true,
    "shopRealPriceFlag": true,
    "needAuditFlag": false,
    "specialComponentFee": 0.0,
    "orderInstructionEnglish": "",
    "moistureSensitivityLevelEn": "MSL 1",
    "hotFlag": null,
    "storyGoods": false,
    "matchedPartDetail": "FH (Guangdong Fenghua Advanced Tech)1nF 50V X7R ±10% 0402 Multilayer Ceramic Capacitors MLCC - SMD/SMT ROHS"
  },
  "message": null
}