{
  "code": 200,
  "data": {
    "componentCode": "C15850",
    "componentBrandEn": "Samsung Electro-Mechanics",
    "componentModelEn": "CL21A106KAYNNNE",
    "componentImageUrl": "https://assets.lcsc.com/images/lcsc/900x900/20180914_Samsung-Electro-Mechanics-CL21A106KAYNNNE_C15850_front_10.jpg",
    "productBigImageAccessId": null,
    "dataManualUrl": "https://www.lcsc.com/datasheet/lcsc_datasheet_2304140030_Samsung-Electro-Mechanics-CL21A106KAYNNNE_C15850.pdf",
    "dataManualFileAccessId": "8579706853615591424",
    "dataManualOfficialLink": "",
    "componentName": "Samsung Electro-Mechanics CL21A106KAYNNNE",
    "minImage": "https://assets.lcsc.com/images/lcsc/96x96/20180914_Samsung-Electro-Mechanics-CL21A106KAYNNNE_C15850_front_10.jpg",
    "minImageAccessId": null,
    "imageList": [
      {
        "productImage": "https://assets.lcsc.com/images/lcsc/96x96/20180914_Samsung-Electro-Mechanics-CL21A106KAYNNNE_C15850_front_10.jpg",
        "productImageAccessId": "",
        "productBigImage": "https://assets.lcsc.com/images/lcsc/900x900/20180914_Samsung-Electro-Mechanics-CL21A106KAYNNNE_C15850_front_10.jpg",
        "productBigImageAccessId": "",
        "fileType": 0
      },
      {
        "productImage": "https://assets.lcsc.com/images/lcsc/96x96/20180914_Samsung-Electro-Mechanics-CL21A106KAYNNNE_C15850_back_10.jpg",
        "productImageAccessId": "",
        "productBigImage": "https://assets.lcsc.com/images/lcsc/900x900/20180914_Samsung-Electro-Mechanics-CL21A106KAYNNNE_C15850_back_10.jpg",
        "productBigImageAccessId": "",
        "fileType": 0
      },
      {
        "productImage": "https://assets.lcsc.com/images/lcsc/96x96/20180914_Samsung-Electro-Mechanics-CL21A106KAYNNNE_C15850_blank.jpg",
        "productImageAccessId": "",
        "productBigImage": "https://assets.lcsc.com/images/lcsc/900x900/20180914_Samsung-Electro-Mechanics-CL21A106KAYNNNE_C15850_blank.jpg",
        "productBigImageAccessId": "",
        "fileType": 0
      },
      {
        "productImage": "https://assets.lcsc.com/images/lcsc/96x96/20180914_Samsung-Electro-Mechanics-CL21A106KAYNNNE_C15850_package_10.jpg",
        "productImageAccessId": "",
        "productBigImage": "https://assets.lcsc.com/images/lcsc/900x900/20180914_Samsung-Electro-Mechanics-CL21A106KAYNNNE_C15850_package_10.jpg",
        "productBigImageAccessId": "",
        "fileType": 0
      }
    ],
    "manufacturerBlackFlag": null,
    "componentNameEn": "Samsung Electro-Mechanics CL21A106KAYNNNE",
    "componentSpecificationEn": "0805",
    "describe": "10uF 25V X5R ±10% 0805 Multilayer Ceramic Capacitors MLCC - SMD/SMT ROHS",
    "attributes": [
      {
        "attribute_name_en": "Voltage Rating",
        "component_code": "C15850",
        "attribute_value_name": "25V"
      },
      {
        "attribute_name_en": "Tolerance",
        "component_code": "C15850",
        "attribute_value_name": "±10%"
      },
      {
        "attribute_name_en": "Capacitance",
        "component_code": "C15850",
        "attribute_value_name": "10uF"
      },
      {
        "attribute_name_en": "Temperature Coefficient",
        "component_code": "C15850",
        "attribute_value_name": "X5R"
      }
    ],
    "rankScore": null,
    "firstSortName": "Capacitors",
    "secondSortName": "Multilayer Ceramic Capacitors MLCC - SMD/SMT",
    "componentBrandHigh": null,
    "remarkHigh": null,
    "componentModelHigh": null,
    "componentCodeHigh": null,
    "componentSpecificationHigh": null,
    "rohsFlag": 1,
    "assemblyComponentFlag": false,
    "lcscComponentId": 16532,
    "componentDesignator": "C",
    "componentSource": "shop",
    "stockCount": 3100663,
    "overseasStockCount": 3100663,
    "prices": [
      {
        "componentPriceKeyId": null,
        "componentPriceAccessId": null,
        "lcscComponentId": null,
        "componentCode": "C15850",
        "startNumber": 1,
        "endNumber": 199,
        "productPrice": 0.0108,
        "erpComponentPriceKeyId": 263793521,
        "createTime": null,
        "updateTime": null,
        "deleted": false,
        "lcscPriceRangeCoefficient": 1
      },
      {
        "componentPriceKeyId": null,
        "componentPriceAccessId": null,
        "lcscComponentId": null,
        "componentCode": "C15850",
        "startNumber": 200,
        "endNumber": 599,
        "productPrice": 0.0082,
        "erpComponentPriceKeyId": 263793534,
        "createTime": null,
        "updateTime": null,
        "deleted": false,
        "lcscPriceRangeCoefficient": 1
      },
      {
        "componentPriceKeyId": null,
        "componentPriceAccessId": null,
        "lcscComponentId": null,
        "componentCode": "C15850",
        "startNumber": 600,
        "endNumber": 1999,
        "productPrice": 0.0071,
        "erpComponentPriceKeyId": 263793528,
        "createTime": null,
        "updateTime": null,
        "deleted": false,
        "lcscPriceRangeCoefficient": 1
      },
      {
        "componentPriceKeyId": null,
        "componentPriceAccessId": null,
        "lcscComponentId": null,
        "componentCode": "C15850",
        "startNumber": 2000,
        "endNumber": 9999,
        "productPrice": 0.0063,
        "erpComponentPriceKeyId": 263793541,
        "createTime": null,
        "updateTime": null,
        "deleted": false,
        "lcscPriceRangeCoefficient": 1
      },
      {
        "componentPriceKeyId": null,
        "componentPriceAccessId": null,
        "lcscComponentId": null,
        "componentCode": "C15850",
        "startNumber": 10000,
        "endNumber": 19999,
        "productPrice": 0.0059,
        "erpComponentPriceKeyId": 263793527,
        "createTime": null,
        "updateTime": null,
        "deleted": false,
        "lcscPriceRangeCoefficient": 1
      },
      {
        "componentPriceKeyId": null,
        "componentPriceAccessId": null,
        "lcscComponentId": null,
        "componentCode": "C15850",
        "startNumber": 20000,
        "endNumber": -1,
        "productPrice": 0.0057,
        "erpComponentPriceKeyId": 263793542,
        "createTime": null,
        "updateTime": null,
        "deleted": false,
        "lcscPriceRangeCoefficient": 1
      }
    ],
    "jlcPrices": null,
    "encapsulationUnit": "PCS",
    "encapsulationNumber": 2000,
    "componentTypeEn": null,
    "xrayFlag": false,
    "componentLibraryType": "base",
    "leastNumber": 20,
    "leastNumberPrice": 0.032,
    "lcscGoodsUrl": "https://www.lcsc.com/product-detail/multilayer-ceramic-capacitors-mlcc-smd-smt_samsung-electro-mechanics-cl21a106kaynnne_C15850.html/?href=jlc-SMT/?href=jlc-SMT",
    "erpComponentName": "10uF ±10% 25V",
    "lossNumber": 10,
    "secondTypeNameEn": "Multilayer Ceramic Capacitors MLCC - SMD/SMT",
    "firstTypeNameEn": "Capacitors",
    "secondTypeNameId": 2929,
    "firstTypeNameId": 2,
    "warehouseCode": "sz",
    "warehouseName": "深圳",
    "canPresaleNumber": 2243427,
    "minPresaleNumber": 0,
    "theRatio": null,
    "componentStatus": "yes",
    "assemblyMode": "smtWeld",
    "assemblyModeBatch": "smtWeld",
    "assemblyProcess": "SMT",
    "minPurchaseNum": 1,
    "initialPrice": 0.0108,
    "minPresalePrice": null,
    "componentPresaleType": null,
    "preMinPurchaseNum": 1208,
    "providerInfos": null,
    "componentProductType": 0,
    "isBuyComponent": "1",
    "noBuyReason": null,
    "replaceUrlSuffix": null,
    "componentAlternativesCode": null,
    "alternativesLcscComponentId": null,
    "leastPatchNumber": 20,
    "fixtureFlag": false,
    "fullReelPrice": null,
    "recentBuyNum": null,
    "recentBuyUnitPrice": null,
    "buyCustomerCode": null,
    "eccnCode": "EAR99",
    "allowPostFlag": true,
    "overseasComponentCatalogBizKey": 385244381135388676,
    "overseasComponentBrandBizKey": "385285311687561217",
    "catalogBlackFlag": null,
    "shopShowPriceFlag": true,
    "shopShowForeignPriceFlag": true,
    "shopRealPriceFlag": true,
    "needAuditFlag": false,
    "specialComponentFee": 0.0,
    "orderInstructionEnglish": "",
    "moistureSensitivityLevelEn": "MSL 1",
    "hotFlag": null,
    "storyGoods": false,
    "matchedPartDetail": "Samsung Electro-Mechanics10uF 25V X5R ±10% 0805 Multilayer Ceramic Capacitors MLCC - SMD/SMT ROHS"
  },
  "message": null
}